setup.py
rivamap/__init__.py
rivamap/delineate.py
rivamap/georef.py
rivamap/preprocess.py
rivamap/singularity_index.py
rivamap/visualization.py
rivamap.egg-info/PKG-INFO
rivamap.egg-info/SOURCES.txt
rivamap.egg-info/dependency_links.txt
rivamap.egg-info/requires.txt
rivamap.egg-info/top_level.txt