Metadata-Version: 1.1
Name: rivamap
Version: 1.0
Summary: An automated river analysis and mapping engine.
Home-page: https://github.com/isikdogan/rivamap
Author: Leo Isikdogan
Author-email: leo@isikdogan.com
License: UNKNOWN
Keywords: remote sensing,landsat,satellite,river
Platform: UNKNOWN
Classifier: Development Status :: 4 - Beta
Classifier: Topic :: Utilities
Classifier: Programming Language :: Python :: 2.7
